dragonfly_idaice/__init__.py
dragonfly_idaice/__main__.py
dragonfly_idaice/_extend_dragonfly.py
dragonfly_idaice/writer.py
dragonfly_idaice/cli/__init__.py
dragonfly_idaice/cli/translate.py
dragonfly_idaice/properties/__init__.py
dragonfly_idaice/properties/model.py
dragonfly_idaice-0.1.0.dist-info/LICENSE
dragonfly_idaice-0.1.0.dist-info/METADATA
dragonfly_idaice-0.1.0.dist-info/WHEEL
dragonfly_idaice-0.1.0.dist-info/entry_points.txt
dragonfly_idaice-0.1.0.dist-info/top_level.txt
dragonfly_idaice-0.1.0.dist-info/RECORD
