Metadata-Version: 2.1
Name: dragonfly-idaice
Version: 0.1.0
Summary: Dragonfly extension for export to IES-VE GEM file format
Home-page: https://github.com/ladybug-tools/dragonfly-idaice
Author: Ladybug Tools
Author-email: info@ladybug.tools
License: AGPL-3.0
Classifier: Programming Language :: Python :: 3.7
Classifier: Programming Language :: Python :: 3.10
Classifier: Programming Language :: Python :: 3.12
Classifier: Programming Language :: Python :: Implementation :: CPython
Classifier: License :: OSI Approved :: GNU Affero General Public License v3
Classifier: Operating System :: OS Independent
License-File: LICENSE
Requires-Dist: dragonfly-core>=1.65.3
Requires-Dist: honeybee-idaice==1.2.0
